differnet/__init__.py
differnet/default_conf.py
differnet/differnet_util.py
differnet/freia_funcs.py
differnet/model.py
differnet/multi_transform_loader.py
tests/__init__.py
differnet_zerobox-0.1.9.dist-info/LICENSE
differnet_zerobox-0.1.9.dist-info/METADATA
differnet_zerobox-0.1.9.dist-info/WHEEL
differnet_zerobox-0.1.9.dist-info/top_level.txt
differnet_zerobox-0.1.9.dist-info/RECORD
