Metadata-Version: 2.1
Name: differnet-zerobox
Version: 0.1.9
Summary: A training core function that can be installed for various projects
Home-page: https://github.com/zerobox-ai/pydiffernet
Author: zerobox
Author-email: dev@zerobox.ai
License: UNKNOWN
Project-URL: Bug Tracker, https://github.com/zerobox-ai/pydiffernet/issues
Keywords: differnet,zerobox
Platform: UNKNOWN
Classifier: Programming Language :: Python :: 3
Classifier: License :: OSI Approved :: MIT License
Classifier: Operating System :: OS Independent
Requires-Python: >=3.8
Requires-Dist: scikit-learn (>=0.22)
Requires-Dist: scipy (>=1.3.2)
Requires-Dist: numpy (>=1.17.4)
Requires-Dist: torch (==1.8.1)
Requires-Dist: torchvision (==0.9.1)
Requires-Dist: matplotlib (>=3.0.3)
Requires-Dist: tqdm (>=4.59.0)
Requires-Dist: opencv-python (>=4.5.1)
